meeting_scheduler/__init__.py
meeting_scheduler/scheduler.py
tests/__init__.py
tests/test_scheduler.py
meeting_scheduler-0.0.3.dist-info/LICENSE
meeting_scheduler-0.0.3.dist-info/METADATA
meeting_scheduler-0.0.3.dist-info/WHEEL
meeting_scheduler-0.0.3.dist-info/top_level.txt
meeting_scheduler-0.0.3.dist-info/RECORD
