Metadata-Version: 2.1
Name: meeting-scheduler
Version: 0.0.3
Summary: A meeting scheduler package
Home-page: https://github.com/wesyoung9987/meetingscheduler
Author: Wes Young
Author-email: wes.young14@gmail.com
License: UNKNOWN
Platform: UNKNOWN
Classifier: Programming Language :: Python :: 2
Classifier: License :: OSI Approved :: MIT License
Classifier: Operating System :: OS Independent
